example_package_1_1/__init__.py
example_package_1_1/example.py
example_package_1_1/subpackage_1/__init__.py
example_package_1_1/subpackage_1/sub_example.py
example_package_2_2/__init__.py
example_package_2_2/example_2.py
example_pkg_AGAIN_2-0.0.5.dist-info/LICENSE
example_pkg_AGAIN_2-0.0.5.dist-info/METADATA
example_pkg_AGAIN_2-0.0.5.dist-info/WHEEL
example_pkg_AGAIN_2-0.0.5.dist-info/top_level.txt
example_pkg_AGAIN_2-0.0.5.dist-info/RECORD
